esphome_dashboard/__init__.py
esphome_dashboard/base.template.html
esphome_dashboard/base_with_header_footer.template.html
esphome_dashboard/index.template.html
esphome_dashboard/login.template.html
esphome_dashboard/static/css/esphome-2.css
esphome_dashboard/static/firmware/bootloader.bin
esphome_dashboard/static/firmware/ota.bin
esphome_dashboard/static/firmware/partitions.bin
esphome_dashboard/static/fonts/codicon.ttf
esphome_dashboard/static/fonts/material-icons/LICENSE
esphome_dashboard/static/fonts/material-icons/MaterialIcons-Regular.woff
esphome_dashboard/static/fonts/material-icons/MaterialIcons-Regular.woff2
esphome_dashboard/static/fonts/material-icons/README.md
esphome_dashboard/static/fonts/material-icons/material-icons.css
esphome_dashboard/static/images/favicon.ico
esphome_dashboard/static/images/logo-text.svg
esphome_dashboard/static/js/esphome/c.1a5bfb59.js
esphome_dashboard/static/js/esphome/c.1a67df3b.js
esphome_dashboard/static/js/esphome/c.1f05f534.js
esphome_dashboard/static/js/esphome/c.1fea68dd.js
esphome_dashboard/static/js/esphome/c.286ad693.js
esphome_dashboard/static/js/esphome/c.2fd5868c.js
esphome_dashboard/static/js/esphome/c.310cede1.js
esphome_dashboard/static/js/esphome/c.31bc909c.js
esphome_dashboard/static/js/esphome/c.417d3d2d.js
esphome_dashboard/static/js/esphome/c.440fff61.js
esphome_dashboard/static/js/esphome/c.4537999f.js
esphome_dashboard/static/js/esphome/c.5cd5d307.js
esphome_dashboard/static/js/esphome/c.5e023db7.js
esphome_dashboard/static/js/esphome/c.79f1d4d7.js
esphome_dashboard/static/js/esphome/c.7aa314ef.js
esphome_dashboard/static/js/esphome/c.7af3b66b.js
esphome_dashboard/static/js/esphome/c.7e8b4fbe.js
esphome_dashboard/static/js/esphome/c.882a59fb.js
esphome_dashboard/static/js/esphome/c.9025cf52.js
esphome_dashboard/static/js/esphome/c.98107f59.js
esphome_dashboard/static/js/esphome/c.984ce2b9.js
esphome_dashboard/static/js/esphome/c.98cb9260.js
esphome_dashboard/static/js/esphome/c.9dbdb9a2.js
libretuya_esphome_dashboard-20230214.0.dist-info/LICENSE
libretuya_esphome_dashboard-20230214.0.dist-info/METADATA
libretuya_esphome_dashboard-20230214.0.dist-info/WHEEL
libretuya_esphome_dashboard-20230214.0.dist-info/top_level.txt
libretuya_esphome_dashboard-20230214.0.dist-info/RECORD
